tabler/__init__.py
tabler/__version__.py
tabler/exceptions.py
tabler/table.py
tabler/tablerow.py
tabler/tabletypes/__init__.py
tabler/tabletypes/basetabletype.py
tabler/tabletypes/csv.py
tabler/tabletypes/html.py
tabler/tabletypes/ods.py
tabler/tabletypes/xlsx.py
tabler/tohtml/__init__.py
tabler/tohtml/table_template.html
tabler/tohtml/tohtml.py
tabler-2.4.2.dist-info/LICENSE
tabler-2.4.2.dist-info/WHEEL
tabler-2.4.2.dist-info/METADATA
tabler-2.4.2.dist-info/RECORD
