Metadata-Version: 2.1
Name: tabler
Version: 2.4.2
Summary: Simple interface for tabulated data and .csv files
Home-page: https://github.com/lukeshiner/tabler
License: MIT
Keywords: table,csv,simple
Author: Luke Shiner
Author-email: luke@lukeshiner.com
Requires-Python: >=3.7,<4.0
Classifier: Development Status :: 5 - Production/Stable
Classifier: Intended Audience :: Developers
Classifier: License :: OSI Approved :: MIT License
Classifier: Natural Language :: English
Classifier: Operating System :: OS Independent
Classifier: Programming Language :: Python :: 3
Classifier: Programming Language :: Python :: 3.10
Classifier: Programming Language :: Python :: 3.7
Classifier: Programming Language :: Python :: 3.8
Classifier: Programming Language :: Python :: 3.9
Classifier: Programming Language :: Python :: Implementation :: CPython
Classifier: Topic :: Other/Nonlisted Topic
Classifier: Topic :: Utilities
Requires-Dist: jinja2 (>=3.0.0)
Requires-Dist: openpyxl (>=3.0.3)
Requires-Dist: pyexcel-ods3 (>=0.6.0)
Requires-Dist: requests (>=2.25.1)
Requires-Dist: urllib3 (>=1.25.8)
Project-URL: Documentation, https://tabler.readthedocs.io/en/latest/
Project-URL: Repository, https://github.com/lukeshiner/tabler
